[
  {"leagueId": 39, "season": 2024},
  {"leagueId": 140, "season": 2024},
  {"leagueId": 135, "season": 2024},
  {"leagueId": 78, "season": 2024},
  {"leagueId": 61, "season": 2024},
  {"leagueId": 88, "season": 2024},
  {"leagueId": 333, "season": 2024},
  {"leagueId": 94, "season": 2024},
  {"leagueId": 235, "season": 2024},
  {"leagueId": 10, "season": 2024},
  {"leagueId": 2, "season": 2024},
  {"leagueId": 3, "season": 2024},
  {"leagueId": 5, "season": 2024},
  {"leagueId": 30, "season": 2026},
  {"leagueId": 32, "season": 2026},
  {"leagueId": 34, "season": 2026},
  {"leagueId": 848, "season": 2024},
  {"leagueId": 203, "season": 2024},
  {"leagueId": 253, "season": 2024},
  {"leagueId": 307, "season": 2024}
]
